defectdojo_cli/__init__.py
defectdojo_cli/__main__.py
defectdojo_cli/engagements.py
defectdojo_cli/findings.py
defectdojo_cli/tests.py
defectdojo_cli/util.py
defectdojo_cli-0.7.1.dist-info/AUTHORS
defectdojo_cli-0.7.1.dist-info/LICENSE
defectdojo_cli-0.7.1.dist-info/METADATA
defectdojo_cli-0.7.1.dist-info/WHEEL
defectdojo_cli-0.7.1.dist-info/entry_points.txt
defectdojo_cli-0.7.1.dist-info/pbr.json
defectdojo_cli-0.7.1.dist-info/top_level.txt
defectdojo_cli-0.7.1.dist-info/RECORD
