Metadata-Version: 2.1
Name: defectdojo-cli
Version: 0.7.1
Summary: CLI Wrapper for DefectDojo using APIv2
Author: Luiz Paulo Souto Monteiro
Author-email: lpsmonteiro2@gmail.com
License: MIT
Project-URL: Source Code, https://github.com/adiffpirate/defectdojo-cli
Platform: UNKNOWN
Classifier: Development Status :: 4 - Beta
Classifier: Programming Language :: Python :: 3 :: Only
Classifier: License :: OSI Approved :: MIT License
Classifier: Operating System :: OS Independent
Requires-Python: >=3.6
License-File: LICENSE
License-File: AUTHORS
Requires-Dist: requests
Requires-Dist: tabulate
